atrium/__init__.py
atrium/api_client.py
atrium/configuration.py
atrium/rest.py
atrium/api/__init__.py
atrium/api/accounts_api.py
atrium/api/atrium_client.py
atrium/api/connect_widget_api.py
atrium/api/holdings_api.py
atrium/api/identity_api.py
atrium/api/institutions_api.py
atrium/api/members_api.py
atrium/api/merchants_api.py
atrium/api/statements_api.py
atrium/api/transactions_api.py
atrium/api/users_api.py
atrium/api/verification_api.py
atrium/models/__init__.py
atrium/models/account.py
atrium/models/account_number.py
atrium/models/account_numbers_response_body.py
atrium/models/account_owner.py
atrium/models/account_owners_response_body.py
atrium/models/account_response_body.py
atrium/models/accounts_response_body.py
atrium/models/challenge.py
atrium/models/challenge_image_option.py
atrium/models/challenge_option.py
atrium/models/challenges_response_body.py
atrium/models/connect_widget.py
atrium/models/connect_widget_request_body.py
atrium/models/connect_widget_response_body.py
atrium/models/credential_option.py
atrium/models/credential_request.py
atrium/models/credential_response.py
atrium/models/credentials_response_body.py
atrium/models/holding.py
atrium/models/holding_response_body.py
atrium/models/holdings_response_body.py
atrium/models/institution.py
atrium/models/institution_response_body.py
atrium/models/institutions_response_body.py
atrium/models/member.py
atrium/models/member_connection_status.py
atrium/models/member_connection_status_response_body.py
atrium/models/member_create_request.py
atrium/models/member_create_request_body.py
atrium/models/member_response_body.py
atrium/models/member_resume_request.py
atrium/models/member_resume_request_body.py
atrium/models/member_update_request.py
atrium/models/member_update_request_body.py
atrium/models/members_response_body.py
atrium/models/merchant.py
atrium/models/merchant_location.py
atrium/models/merchant_location_response_body.py
atrium/models/merchant_locations_response_body.py
atrium-2.11.7.dist-info/LICENSE
atrium-2.11.7.dist-info/METADATA
atrium-2.11.7.dist-info/WHEEL
atrium-2.11.7.dist-info/top_level.txt
atrium-2.11.7.dist-info/RECORD
