Metadata-Version: 2.1
Name: atrium
Version: 2.11.7
Summary: MX API
Home-page: https://atrium.mx.com
Author-email: 
License: UNKNOWN
Keywords: MX,MX API
Platform: UNKNOWN
License-File: LICENSE
Requires-Dist: urllib3 (>=1.15)
Requires-Dist: six (>=1.10)
Requires-Dist: certifi
Requires-Dist: python-dateutil
